LICENSE
README.md
setup.py
sunnyday_YG/__init__.py
sunnyday_YG/sunnyday.py
sunnyday_YG.egg-info/PKG-INFO
sunnyday_YG.egg-info/SOURCES.txt
sunnyday_YG.egg-info/dependency_links.txt
sunnyday_YG.egg-info/requires.txt
sunnyday_YG.egg-info/top_level.txt