Metadata-Version: 2.1
Name: sunnyday-YG
Version: 1.0.0
Summary: Weather forecast data
Home-page: https://github.com/YohannesGetu/Weather-Forecast-Package-python
Author: Yohannes Getu
Author-email: nede.evoli@gmail.com
License: MIT
Keywords: weather,forecast,openweather
Platform: UNKNOWN
License-File: LICENSE
